MANIFEST.in
README.rst
setup.py
sphinxcontrib/__init__.py
sphinxcontrib/jsontest/__init__.py
sphinxcontrib/jsontest/_static/highlight.css
sphinxcontrib/jsontest/_static/highlight.pack.js
sphinxcontrib/jsontest/_static/jsontest.css
sphinxcontrib/jsontest/_static/jsontest.js
sphinxcontrib/jsontest/_static/tv4.min.js
sphinxcontrib/jsontest/templates/api_test.html
sphinxcontrib_jsontest.egg-info/PKG-INFO
sphinxcontrib_jsontest.egg-info/SOURCES.txt
sphinxcontrib_jsontest.egg-info/dependency_links.txt
sphinxcontrib_jsontest.egg-info/namespace_packages.txt
sphinxcontrib_jsontest.egg-info/not-zip-safe
sphinxcontrib_jsontest.egg-info/pbr.json
sphinxcontrib_jsontest.egg-info/requires.txt
sphinxcontrib_jsontest.egg-info/top_level.txt