Metadata-Version: 1.0
Name: sphinxcontrib-jsontest
Version: 0.1.3
Summary: Sphinx extension allows you to test json apis
Home-page: https://github.com/stephenbm/sphinxcontrib.jsontest
Author: Stephen Breyer-Menke
Author-email: steve.bm@gmail.com
License: Public domain
Platform: UNKNOWN
